treibstoff/__init__.py
treibstoff/bundle/loading-spokes.svg
treibstoff/bundle/treibstoff.bundle.js
treibstoff/bundle/treibstoff.bundle.min.js
treibstoff/bundle/treibstoff.css
treibstoff-0.4.0.dist-info/LICENSE.rst
treibstoff-0.4.0.dist-info/METADATA
treibstoff-0.4.0.dist-info/WHEEL
treibstoff-0.4.0.dist-info/top_level.txt
treibstoff-0.4.0.dist-info/RECORD
