Metadata-Version: 2.1
Name: treibstoff
Version: 0.4.0
Summary: A set of useful javascript tools for writing browser based applications (or parts of it).
Home-page: https://github.com/conestack/treibstoff
Author: Conestack Contributors
Author-email: dev@conestack.org
License: Simplified BSD
Classifier: Environment :: Web Environment
Classifier: Operating System :: OS Independent
Classifier: Programming Language :: JavaScript
Classifier: Topic :: Internet :: WWW/HTTP :: Dynamic Content
License-File: LICENSE.rst
Requires-Dist: setuptools
Requires-Dist: webresource
Provides-Extra: docs
Requires-Dist: Jinja2 <3.0 ; extra == 'docs'
Requires-Dist: markupsafe <2.1.0 ; extra == 'docs'
Requires-Dist: Sphinx ; extra == 'docs'
Requires-Dist: sphinx-conestack-theme ; extra == 'docs'
Requires-Dist: sphinx-js ; extra == 'docs'
